{
  "data": {
    "type": 0,
    "openers": [
      [
        -777886662,
        -43627786,
        -2114708613,
        -1931975085
      ]
    ],
    "inventories": [
      {
        "chest": {
          "Items": [
            {
              "Slot": 0,
              "count": 3,
              "id": "minecraft:string"
            },
            {
              "Slot": 1,
              "count": 1,
              "components": {
                "minecraft:damage": 50
              },
              "id": "minecraft:golden_chestplate"
            },
            {
              "Slot": 2,
              "count": 1,
              "id": "minecraft:diamond_horse_armor"
            },
            {
              "Slot": 3,
              "count": 1,
              "id": "cardiac:life_bottle"
            },
            {
              "Slot": 4,
              "count": 1,
              "components": {
                "relics:data": {
                  "abilities": {
                    "abilities": {
                      "dissection": {
                        "stats": {
                          "time": {
                            "initialValue": 5.50717
                          },
                          "distance": {
                            "initialValue": 24.55084
                          }
                        },
                        "lock": {
                          "breaks": 5
                        },
                        "research": {
                          "links": {},
                          "researched": 0
                        },
                        "extender": {
                          "ticking": 0,
                          "cooldown": 0,
                          "cooldownCap": 0
                        },
                        "points": 0
                      }
                    }
                  },
                  "leveling": {
                    "luck": 0,
                    "experience": 0,
                    "level": 0,
                    "points": 0
                  }
                }
              },
              "id": "relics:space_dissector"
            }
          ]
        },
        "uuid": [
          -777886662,
          -43627786,
          -2114708613,
          -1931975085
        ]
      }
    ],
    "uuid": [
      1644265804,
      -1947972151,
      -1432372728,
      -507077633
    ],
    "seed": 2003802887649176927,
    "name": "{\"translate\":\"container.barrel\"}",
    "blockType": 2,
    "key": "lootr/6/62/6201814c-8be4-4dc9-aa9f-ba08e1c69bff",
    "dimension": "minecraft:the_nether",
    "hasBeenOpened": 1,
    "position": [
      -2858,
      99,
      -1805
    ],
    "size": 27,
    "actualOpeners": [
      [
        -777886662,
        -43627786,
        -2114708613,
        -1931975085
      ]
    ],
    "table": "betterfortresses:chests/keep"
  },
  "DataVersion": 3955,
  "brewinandchewin:data_version": 100
}