{
  "data": {
    "type": 0,
    "openers": [
      [
        1095242867,
        -529184618,
        -1379070319,
        -929691937
      ]
    ],
    "inventories": [
      {
        "chest": {
          "Items": [
            {
              "Slot": 0,
              "count": 2,
              "id": "minecraft:dark_oak_log"
            },
            {
              "Slot": 1,
              "count": 4,
              "id": "minecraft:carrot"
            },
            {
              "Slot": 2,
              "count": 1,
              "components": {
                "minecraft:potion_contents": {
                  "potion": "ars_nouveau:mana_regen_potion_long"
                }
              },
              "id": "minecraft:potion"
            },
            {
              "Slot": 3,
              "count": 7,
              "id": "minecraft:wheat"
            },
            {
              "Slot": 4,
              "count": 1,
              "id": "cardiac:life_bottle"
            },
            {
              "Slot": 6,
              "count": 1,
              "id": "exposure_expanded:scan_pincushion_filter"
            },
            {
              "Slot": 8,
              "count": 2,
              "id": "farmersdelight:onion_crate"
            }
          ]
        },
        "uuid": [
          1095242867,
          -529184618,
          -1379070319,
          -929691937
        ]
      }
    ],
    "uuid": [
      1193946610,
      211307824,
      -1829976482,
      -1435984064
    ],
    "seed": 3267794423237622248,
    "name": "{\"translate\":\"container.chest\"}",
    "blockType": 0,
    "key": "lootr/4/47/472a2df2-0c98-4d30-92ec-c65eaa689f40",
    "dimension": "minecraft:overworld",
    "hasBeenOpened": 1,
    "position": [
      1301,
      118,
      139
    ],
    "size": 27,
    "actualOpeners": [
      [
        1095242867,
        -529184618,
        -1379070319,
        -929691937
      ]
    ],
    "table": "minecraft:chests/pillager_outpost"
  },
  "DataVersion": 3955,
  "brewinandchewin:data_version": 100
}