{
  "data": {
    "type": 0,
    "openers": [
      [
        -777886662,
        -43627786,
        -2114708613,
        -1931975085
      ]
    ],
    "inventories": [
      {
        "chest": {
          "Items": [
            {
              "Slot": 0,
              "count": 1,
              "id": "minecraft:wheat_seeds"
            },
            {
              "Slot": 1,
              "count": 3,
              "id": "minecraft:coal"
            },
            {
              "Slot": 3,
              "count": 1,
              "id": "minecraft:carrot"
            },
            {
              "Slot": 4,
              "count": 2,
              "id": "minecraft:wheat_seeds"
            },
            {
              "Slot": 6,
              "count": 1,
              "id": "minecraft:beetroot_seeds"
            },
            {
              "Slot": 7,
              "count": 2,
              "id": "minecraft:coal"
            },
            {
              "Slot": 8,
              "count": 1,
              "id": "minecraft:torch"
            },
            {
              "Slot": 11,
              "count": 1,
              "id": "minecraft:stone_shovel"
            },
            {
              "Slot": 12,
              "count": 1,
              "id": "minecraft:carrot"
            },
            {
              "Slot": 13,
              "count": 1,
              "components": {
                "minecraft:stored_enchantments": {
                  "levels": {
                    "minecraft:sweeping_edge": 1
                  }
                }
              },
              "id": "minecraft:enchanted_book"
            },
            {
              "Slot": 14,
              "count": 1,
              "id": "minecraft:beetroot_seeds"
            },
            {
              "Slot": 15,
              "count": 1,
              "id": "minecraft:beetroot_seeds"
            },
            {
              "Slot": 17,
              "count": 1,
              "id": "minecraft:carrot"
            },
            {
              "Slot": 19,
              "count": 1,
              "id": "minecraft:beetroot_seeds"
            },
            {
              "Slot": 20,
              "count": 3,
              "id": "minecraft:torch"
            },
            {
              "Slot": 21,
              "count": 1,
              "id": "minecraft:wheat_seeds"
            },
            {
              "Slot": 23,
              "count": 1,
              "id": "minecraft:carrot"
            },
            {
              "Slot": 24,
              "count": 1,
              "id": "minecraft:carrot"
            },
            {
              "Slot": 25,
              "count": 1,
              "id": "minecraft:stone_shovel"
            }
          ]
        },
        "uuid": [
          -777886662,
          -43627786,
          -2114708613,
          -1931975085
        ]
      }
    ],
    "uuid": [
      355495778,
      -924038708,
      -1683779139,
      -1391920765
    ],
    "seed": 8198480500687436647,
    "name": "{\"translate\":\"container.chest\"}",
    "blockType": 0,
    "key": "lootr/1/15/15306f62-c8ec-49cc-9ba3-91bdad08f983",
    "dimension": "amplidim:overworld",
    "hasBeenOpened": 1,
    "position": [
      833,
      35,
      864
    ],
    "size": 27,
    "actualOpeners": [
      [
        -777886662,
        -43627786,
        -2114708613,
        -1931975085
      ]
    ],
    "table": "betterdungeons:zombie_dungeon/chests/common"
  },
  "DataVersion": 3955,
  "brewinandchewin:data_version": 100
}