{
  "data": {
    "type": 0,
    "openers": [
      [
        -777886662,
        -43627786,
        -2114708613,
        -1931975085
      ]
    ],
    "inventories": [
      {
        "chest": {
          "Items": []
        },
        "uuid": [
          -777886662,
          -43627786,
          -2114708613,
          -1931975085
        ]
      }
    ],
    "uuid": [
      427863791,
      224676586,
      -2031920213,
      849071648
    ],
    "seed": 4914489099340808551,
    "name": "{\"translate\":\"container.chest\"}",
    "blockType": 0,
    "key": "lootr/1/19/1980aeef-0d64-4aea-86e3-5bab329bce20",
    "dimension": "minecraft:overworld",
    "hasBeenOpened": 1,
    "position": [
      1179,
      64,
      -308
    ],
    "size": 27,
    "actualOpeners": [
      [
        -777886662,
        -43627786,
        -2114708613,
        -1931975085
      ]
    ],
    "table": "minecraft:chests/village/village_temple"
  },
  "DataVersion": 3955,
  "brewinandchewin:data_version": 100
}