{
  "data": {
    "type": 0,
    "openers": [
      [
        2001138388,
        -1529393814,
        -1151761747,
        1858955045
      ]
    ],
    "inventories": [
      {
        "chest": {
          "Items": []
        },
        "uuid": [
          2001138388,
          -1529393814,
          -1151761747,
          1858955045
        ]
      }
    ],
    "uuid": [
      658695912,
      1522550585,
      -2016193467,
      2060813603
    ],
    "seed": 9039688481686577721,
    "name": "{\"translate\":\"container.chest\"}",
    "blockType": 0,
    "key": "lootr/2/27/2742e6e8-5ac0-4739-87d3-54457ad58523",
    "dimension": "minecraft:overworld",
    "hasBeenOpened": 1,
    "position": [
      -2444,
      110,
      -813
    ],
    "size": 27,
    "actualOpeners": [
      [
        2001138388,
        -1529393814,
        -1151761747,
        1858955045
      ]
    ],
    "table": "betterarcheology:archeology/chest_catacombs_golden"
  },
  "DataVersion": 3955,
  "brewinandchewin:data_version": 100
}