{
  "data": {
    "type": 0,
    "openers": [
      [
        -1300637667,
        -584760945,
        -1215534361,
        674047685
      ]
    ],
    "inventories": [
      {
        "chest": {
          "Items": []
        },
        "uuid": [
          -1300637667,
          -584760945,
          -1215534361,
          674047685
        ]
      }
    ],
    "uuid": [
      476833605,
      -485798033,
      -1727599809,
      -1213259838
    ],
    "seed": 4301150634517711225,
    "name": "{\"translate\":\"container.barrel\"}",
    "blockType": 2,
    "key": "lootr/1/1c/1c6be745-e30b-4f6f-9906-eb3fb7af1fc2",
    "dimension": "amplidim:overworld",
    "hasBeenOpened": 1,
    "position": [
      -917,
      -24,
      391
    ],
    "size": 27,
    "actualOpeners": [
      [
        -1300637667,
        -584760945,
        -1215534361,
        674047685
      ]
    ],
    "table": "minecraft:chests/abandoned_mineshaft"
  },
  "DataVersion": 3955,
  "brewinandchewin:data_version": 100
}