{
  "data": {
    "type": 0,
    "openers": [
      [
        1433557250,
        -1386395105,
        -1629274564,
        1643515946
      ]
    ],
    "inventories": [
      {
        "chest": {
          "Items": [
            {
              "Slot": 0,
              "count": 2,
              "id": "minecraft:leather"
            },
            {
              "Slot": 1,
              "count": 1,
              "id": "minecraft:leather"
            },
            {
              "Slot": 2,
              "count": 1,
              "id": "minecraft:string"
            },
            {
              "Slot": 8,
              "count": 2,
              "id": "minecraft:gunpowder"
            },
            {
              "Slot": 9,
              "count": 8,
              "id": "minecraft:amethyst_shard"
            },
            {
              "Slot": 10,
              "count": 1,
              "id": "minecraft:string"
            },
            {
              "Slot": 12,
              "count": 1,
              "id": "minecraft:amethyst_shard"
            },
            {
              "Slot": 14,
              "count": 1,
              "id": "minecraft:gunpowder"
            },
            {
              "Slot": 15,
              "count": 2,
              "id": "minecraft:amethyst_shard"
            },
            {
              "Slot": 16,
              "count": 1,
              "id": "minecraft:leather"
            },
            {
              "Slot": 18,
              "count": 1,
              "components": {
                "minecraft:stored_enchantments": {
                  "levels": {
                    "farmersdelight:backstabbing": 2,
                    "minecraft:fire_protection": 3
                  }
                }
              },
              "id": "minecraft:enchanted_book"
            },
            {
              "Slot": 20,
              "count": 1,
              "components": {
                "minecraft:potion_contents": {
                  "potion": "minecraft:harming"
                }
              },
              "id": "minecraft:potion"
            },
            {
              "Slot": 26,
              "count": 2,
              "id": "minecraft:gunpowder"
            }
          ]
        },
        "uuid": [
          1433557250,
          -1386395105,
          -1629274564,
          1643515946
        ]
      }
    ],
    "uuid": [
      942439582,
      -556970654,
      -1614260059,
      -1799012487
    ],
    "seed": -357755267606824555,
    "name": "{\"translate\":\"container.chest\"}",
    "blockType": 0,
    "key": "lootr/3/38/382c7c9e-decd-4d62-9fc8-58a594c53f79",
    "dimension": "amplidim:overworld",
    "hasBeenOpened": 1,
    "position": [
      -474,
      -46,
      314
    ],
    "size": 27,
    "actualOpeners": [
      [
        1433557250,
        -1386395105,
        -1629274564,
        1643515946
      ]
    ],
    "table": "structory:library/high"
  },
  "DataVersion": 3955,
  "brewinandchewin:data_version": 100
}