{
  "data": {
    "type": 0,
    "openers": [
      [
        -1897521421,
        518932583,
        -1765357074,
        1888276970
      ]
    ],
    "inventories": [
      {
        "chest": {
          "Items": []
        },
        "uuid": [
          -1897521421,
          518932583,
          -1765357074,
          1888276970
        ]
      }
    ],
    "uuid": [
      -62926642,
      1068846692,
      -1723977846,
      556906414
    ],
    "seed": -532576736196664711,
    "name": "{\"translate\":\"container.barrel\"}",
    "blockType": 2,
    "key": "lootr/f/fc/fc3fd0ce-3fb5-4e64-993e-2f8a2131b7ae",
    "dimension": "minecraft:overworld",
    "hasBeenOpened": 1,
    "position": [
      399,
      11,
      330
    ],
    "size": 27,
    "actualOpeners": [
      [
        -1897521421,
        518932583,
        -1765357074,
        1888276970
      ]
    ],
    "table": "artifacts:chests/campsite_barrel"
  },
  "DataVersion": 3955,
  "brewinandchewin:data_version": 100
}