{
  "data": {
    "type": 0,
    "openers": [
      [
        -777886662,
        -43627786,
        -2114708613,
        -1931975085
      ]
    ],
    "inventories": [
      {
        "chest": {
          "Items": []
        },
        "uuid": [
          -777886662,
          -43627786,
          -2114708613,
          -1931975085
        ]
      }
    ],
    "uuid": [
      673561808,
      1069369214,
      -1139679918,
      -759338628
    ],
    "seed": -5212705044777702104,
    "name": "{\"translate\":\"container.chest\"}",
    "blockType": 0,
    "key": "lootr/2/28/2825bcd0-3fbd-477e-bc11-dd52d2bd697c",
    "dimension": "minecraft:overworld",
    "hasBeenOpened": 1,
    "position": [
      -4106,
      -16,
      -4060
    ],
    "size": 27,
    "actualOpeners": [
      [
        -777886662,
        -43627786,
        -2114708613,
        -1931975085
      ]
    ],
    "table": "betterstrongholds:chests/grand_library"
  },
  "DataVersion": 3955,
  "brewinandchewin:data_version": 100
}