{
  "data": {
    "type": 0,
    "openers": [
      [
        120605565,
        448350698,
        -1718274565,
        -1481540022
      ],
      [
        -777886662,
        -43627786,
        -2114708613,
        -1931975085
      ]
    ],
    "inventories": [
      {
        "chest": {
          "Items": [
            {
              "Slot": 4,
              "count": 1,
              "id": "minecraft:cobweb"
            },
            {
              "Slot": 6,
              "count": 1,
              "id": "minecraft:coal"
            },
            {
              "Slot": 7,
              "count": 1,
              "id": "minecraft:cobweb"
            },
            {
              "Slot": 15,
              "count": 3,
              "id": "minecraft:coal"
            },
            {
              "Slot": 18,
              "count": 2,
              "id": "minecraft:coal"
            },
            {
              "Slot": 19,
              "count": 3,
              "id": "minecraft:coal"
            },
            {
              "Slot": 21,
              "count": 2,
              "id": "minecraft:coal"
            },
            {
              "Slot": 22,
              "count": 1,
              "id": "minecraft:cobweb"
            },
            {
              "Slot": 24,
              "count": 1,
              "id": "minecraft:cobweb"
            },
            {
              "Slot": 25,
              "count": 1,
              "id": "minecraft:coal"
            }
          ]
        },
        "uuid": [
          120605565,
          448350698,
          -1718274565,
          -1481540022
        ]
      },
      {
        "chest": {
          "Items": [
            {
              "Slot": 10,
              "count": 1,
              "id": "minecraft:diamond_horse_armor"
            },
            {
              "Slot": 12,
              "count": 1,
              "id": "minecraft:apple"
            },
            {
              "Slot": 20,
              "count": 1,
              "id": "minecraft:apple"
            }
          ]
        },
        "uuid": [
          -777886662,
          -43627786,
          -2114708613,
          -1931975085
        ]
      }
    ],
    "uuid": [
      573288602,
      1713850523,
      -1424732930,
      192759438
    ],
    "seed": 1094630735457565979,
    "name": "{\"translate\":\"container.barrel\"}",
    "blockType": 2,
    "key": "lootr/2/22/222bb09a-6627-489b-ab14-4cfe0b7d468e",
    "dimension": "minecraft:overworld",
    "hasBeenOpened": 1,
    "position": [
      -4003,
      -15,
      -3998
    ],
    "size": 27,
    "actualOpeners": [
      [
        120605565,
        448350698,
        -1718274565,
        -1481540022
      ],
      [
        -777886662,
        -43627786,
        -2114708613,
        -1931975085
      ]
    ],
    "table": "betterstrongholds:chests/common"
  },
  "DataVersion": 3955,
  "brewinandchewin:data_version": 100
}