{
  "data": {
    "type": 0,
    "openers": [
      [
        -777886662,
        -43627786,
        -2114708613,
        -1931975085
      ],
      [
        1095242867,
        -529184618,
        -1379070319,
        -929691937
      ],
      [
        -2083853256,
        1488473380,
        -1779687266,
        -272052621
      ]
    ],
    "inventories": [
      {
        "chest": {
          "Items": [
            {
              "Slot": 0,
              "count": 2,
              "id": "minecraft:pumpkin_seeds"
            },
            {
              "Slot": 1,
              "count": 12,
              "id": "minecraft:string"
            },
            {
              "Slot": 2,
              "count": 1,
              "id": "minecraft:diamond_hoe"
            },
            {
              "Slot": 3,
              "count": 1,
              "id": "minecraft:name_tag"
            },
            {
              "Slot": 4,
              "count": 1,
              "id": "minecraft:music_disc_cat"
            },
            {
              "Slot": 5,
              "count": 1,
              "components": {
                "minecraft:potion_contents": {
                  "potion": "ars_nouveau:mana_regen_potion_long"
                }
              },
              "id": "minecraft:potion"
            },
            {
              "Slot": 6,
              "count": 2,
              "id": "minecraft:bone"
            },
            {
              "Slot": 7,
              "count": 1,
              "id": "ars_nouveau:drygmy_shard"
            },
            {
              "Slot": 8,
              "count": 1,
              "id": "extradelight:glow_berry_cheesecake_slice"
            },
            {
              "Slot": 9,
              "count": 1,
              "id": "extradelight:egg_in_the_basket"
            },
            {
              "Slot": 10,
              "count": 1,
              "id": "extradelight:bbq_jar_item"
            },
            {
              "Slot": 11,
              "count": 1,
              "id": "extradelight:ketchup_jar_item"
            },
            {
              "Slot": 12,
              "count": 1,
              "id": "extradelight:mayo_jar_item"
            },
            {
              "Slot": 13,
              "count": 2,
              "id": "extradelight:curry_powder"
            },
            {
              "Slot": 14,
              "count": 1,
              "id": "extradelight:carrot_soup"
            },
            {
              "Slot": 15,
              "count": 1,
              "id": "extradelight:jelly_orange_block_item"
            },
            {
              "Slot": 16,
              "count": 1,
              "id": "extradelight:jelly_brown_block_item"
            },
            {
              "Slot": 17,
              "count": 1,
              "id": "extradelight:fish_flakes"
            },
            {
              "Slot": 18,
              "count": 1,
              "id": "extradelight:mushroom_risotto"
            },
            {
              "Slot": 19,
              "count": 1,
              "id": "extradelight:cooked_cactus"
            }
          ]
        },
        "uuid": [
          -2083853256,
          1488473380,
          -1779687266,
          -272052621
        ]
      },
      {
        "chest": {
          "Items": [
            {
              "Slot": 0,
              "count": 5,
              "id": "minecraft:string"
            },
            {
              "Slot": 1,
              "count": 1,
              "id": "minecraft:diamond_chestplate"
            },
            {
              "Slot": 2,
              "count": 1,
              "components": {
                "supplementaries:quiver_content": {
                  "items": [
                    {
                      "id": "minecraft:tipped_arrow",
                      "count": 1,
                      "components": {
                        "minecraft:potion_contents": {
                          "potion": "minecraft:long_slowness"
                        }
                      }
                    },
                    {
                      "id": "minecraft:tipped_arrow",
                      "count": 3,
                      "components": {
                        "minecraft:potion_contents": {
                          "potion": "minecraft:strong_slowness"
                        }
                      }
                    },
                    {
                      "id": "minecraft:tipped_arrow",
                      "count": 6,
                      "components": {
                        "minecraft:potion_contents": {
                          "potion": "minecraft:turtle_master"
                        }
                      }
                    },
                    {
                      "id": "minecraft:tipped_arrow",
                      "count": 3,
                      "components": {
                        "minecraft:potion_contents": {
                          "potion": "ars_elemental:enderference_potion"
                        }
                      }
                    },
                    {},
                    {}
                  ],
                  "selected_slot": 0
                }
              },
              "id": "supplementaries:quiver"
            },
            {
              "Slot": 3,
              "count": 1,
              "id": "minecraft:bread"
            },
            {
              "Slot": 4,
              "count": 1,
              "components": {
                "minecraft:potion_contents": {
                  "potion": "ars_nouveau:mana_regen_potion"
                }
              },
              "id": "minecraft:potion"
            },
            {
              "Slot": 5,
              "count": 13,
              "id": "minecraft:gunpowder"
            }
          ]
        },
        "uuid": [
          -777886662,
          -43627786,
          -2114708613,
          -1931975085
        ]
      },
      {
        "chest": {
          "Items": [
            {
              "Slot": 0,
              "count": 1,
              "id": "minecraft:music_disc_13"
            },
            {
              "Slot": 1,
              "count": 1,
              "id": "minecraft:chainmail_chestplate"
            },
            {
              "Slot": 2,
              "count": 1,
              "components": {
                "minecraft:potion_contents": {
                  "potion": "ars_nouveau:mana_regen_potion_strong"
                }
              },
              "id": "minecraft:potion"
            },
            {
              "Slot": 3,
              "count": 2,
              "id": "minecraft:coal"
            },
            {
              "Slot": 4,
              "count": 8,
              "id": "minecraft:bone"
            },
            {
              "Slot": 5,
              "count": 3,
              "id": "minecraft:gunpowder"
            },
            {
              "Slot": 7,
              "count": 1,
              "components": {
                "relics:data": {
                  "abilities": {
                    "abilities": {
                      "hold": {
                        "stats": {
                          "duration": {
                            "initialValue": 4.07911
                          }
                        },
                        "lock": {
                          "breaks": 5
                        },
                        "research": {
                          "links": {},
                          "researched": 0
                        },
                        "extender": {
                          "ticking": 0,
                          "cooldown": 0,
                          "cooldownCap": 0
                        },
                        "points": 0
                      }
                    }
                  },
                  "leveling": {
                    "luck": 0,
                    "experience": 0,
                    "level": 0,
                    "points": 0
                  }
                }
              },
              "id": "artifacts:bunny_hoppers"
            },
            {
              "Slot": 8,
              "count": 1,
              "id": "ars_nouveau:starbuncle_shards"
            },
            {
              "Slot": 9,
              "count": 3,
              "id": "ars_nouveau:wilden_wing"
            },
            {
              "Slot": 10,
              "count": 1,
              "id": "extradelight:sweet_berry_pie_slice"
            },
            {
              "Slot": 11,
              "count": 1,
              "id": "extradelight:sugar_cookie"
            },
            {
              "Slot": 12,
              "count": 1,
              "id": "extradelight:sweet_berry_popsicle"
            },
            {
              "Slot": 13,
              "count": 1,
              "id": "extradelight:boiled_egg"
            },
            {
              "Slot": 14,
              "count": 2,
              "id": "extradelight:ketchup_jar_item"
            },
            {
              "Slot": 15,
              "count": 3,
              "id": "extradelight:curry_powder"
            },
            {
              "Slot": 16,
              "count": 1,
              "id": "extradelight:egg_salad_sandwich"
            },
            {
              "Slot": 17,
              "count": 1,
              "id": "extradelight:salisbury_steak"
            },
            {
              "Slot": 18,
              "count": 1,
              "id": "extradelight:pork_tenderloin"
            },
            {
              "Slot": 19,
              "count": 1,
              "id": "extradelight:meat_pie_slice"
            },
            {
              "Slot": 20,
              "count": 1,
              "id": "extradelight:salad"
            },
            {
              "Slot": 21,
              "count": 1,
              "id": "extradelight:riceball"
            },
            {
              "Slot": 22,
              "count": 1,
              "id": "extradelight:riceball_filled"
            }
          ]
        },
        "uuid": [
          1095242867,
          -529184618,
          -1379070319,
          -929691937
        ]
      }
    ],
    "uuid": [
      -1065185499,
      -1375582154,
      -1296421409,
      1681440309
    ],
    "seed": 6266697249442849308,
    "name": "{\"translate\":\"container.chest\"}",
    "blockType": 0,
    "key": "lootr/c/c0/c0828f25-ae02-4836-b2ba-2ddf6438be35",
    "dimension": "minecraft:overworld",
    "hasBeenOpened": 1,
    "position": [
      4635,
      73,
      -329
    ],
    "size": 27,
    "actualOpeners": [
      [
        -777886662,
        -43627786,
        -2114708613,
        -1931975085
      ],
      [
        1095242867,
        -529184618,
        -1379070319,
        -929691937
      ],
      [
        -2083853256,
        1488473380,
        -1779687266,
        -272052621
      ]
    ],
    "table": "minecraft:chests/woodland_mansion"
  },
  "DataVersion": 3955,
  "brewinandchewin:data_version": 100
}