{
  "data": {
    "type": 0,
    "openers": [
      [
        -777886662,
        -43627786,
        -2114708613,
        -1931975085
      ]
    ],
    "inventories": [
      {
        "chest": {
          "Items": [
            {
              "Slot": 11,
              "count": 1,
              "id": "minecraft:salmon"
            },
            {
              "Slot": 14,
              "count": 1,
              "id": "minecraft:water_bucket"
            },
            {
              "Slot": 15,
              "count": 1,
              "id": "minecraft:salmon"
            },
            {
              "Slot": 22,
              "count": 1,
              "id": "minecraft:salmon"
            }
          ]
        },
        "uuid": [
          -777886662,
          -43627786,
          -2114708613,
          -1931975085
        ]
      }
    ],
    "uuid": [
      344713319,
      725501503,
      -1782272111,
      1806608073
    ],
    "seed": 8935173435506994775,
    "name": "{\"translate\":\"container.barrel\"}",
    "blockType": 2,
    "key": "lootr/1/14/148be867-2b3e-463f-95c4-af916baea6c9",
    "dimension": "minecraft:overworld",
    "hasBeenOpened": 1,
    "position": [
      -1904,
      47,
      782
    ],
    "size": 27,
    "actualOpeners": [
      [
        -777886662,
        -43627786,
        -2114708613,
        -1931975085
      ]
    ],
    "table": "stoneholm:fisherman"
  },
  "DataVersion": 3955,
  "brewinandchewin:data_version": 100
}