{
  "data": {
    "type": 0,
    "openers": [
      [
        -777886662,
        -43627786,
        -2114708613,
        -1931975085
      ],
      [
        -1885153931,
        100551408,
        -1506813879,
        988589670
      ]
    ],
    "inventories": [
      {
        "chest": {
          "Items": [
            {
              "Slot": 0,
              "count": 3,
              "id": "supplementaries:bomb"
            },
            {
              "Slot": 1,
              "count": 7,
              "id": "minecraft:coal"
            },
            {
              "Slot": 3,
              "count": 1,
              "components": {
                "relics:data": {
                  "abilities": {
                    "abilities": {
                      "devouring": {
                        "stats": {
                          "frequency": {
                            "initialValue": 138.51597
                          }
                        },
                        "lock": {
                          "breaks": 5
                        },
                        "research": {
                          "links": {},
                          "researched": 0
                        },
                        "extender": {
                          "ticking": 1,
                          "cooldown": 0,
                          "cooldownCap": 0
                        },
                        "points": 0
                      }
                    }
                  },
                  "leveling": {
                    "luck": 0,
                    "experience": 0,
                    "level": 0,
                    "points": 0
                  }
                }
              },
              "id": "artifacts:rooted_boots"
            }
          ]
        },
        "uuid": [
          -1885153931,
          100551408,
          -1506813879,
          988589670
        ]
      },
      {
        "chest": {
          "Items": [
            {
              "Slot": 0,
              "count": 1,
              "id": "minecraft:apple"
            },
            {
              "Slot": 1,
              "count": 1,
              "components": {
                "minecraft:potion_contents": {
                  "potion": "ars_nouveau:mana_regen_potion_long"
                }
              },
              "id": "minecraft:potion"
            },
            {
              "Slot": 4,
              "count": 2,
              "id": "minecraft:iron_ingot"
            },
            {
              "Slot": 6,
              "count": 2,
              "id": "minecraft:iron_ingot"
            },
            {
              "Slot": 8,
              "count": 1,
              "id": "minecraft:apple"
            },
            {
              "Slot": 12,
              "count": 1,
              "id": "minecraft:iron_ingot"
            },
            {
              "Slot": 18,
              "count": 1,
              "id": "minecraft:apple"
            }
          ]
        },
        "uuid": [
          -777886662,
          -43627786,
          -2114708613,
          -1931975085
        ]
      }
    ],
    "uuid": [
      513067604,
      1291927554,
      -2068734418,
      1417979849
    ],
    "seed": -9046917154442847319,
    "name": "{\"translate\":\"container.barrel\"}",
    "blockType": 2,
    "key": "lootr/1/1e/1e94ca54-4d01-4002-84b1-9e2e5484a7c9",
    "dimension": "minecraft:overworld",
    "hasBeenOpened": 1,
    "position": [
      2816,
      -9,
      -3816
    ],
    "size": 27,
    "actualOpeners": [
      [
        -777886662,
        -43627786,
        -2114708613,
        -1931975085
      ],
      [
        -1885153931,
        100551408,
        -1506813879,
        988589670
      ]
    ],
    "table": "minecraft:chests/stronghold_crossing"
  },
  "DataVersion": 3955,
  "brewinandchewin:data_version": 100
}