{
  "data": {
    "type": 0,
    "openers": [
      [
        -777886662,
        -43627786,
        -2114708613,
        -1931975085
      ]
    ],
    "inventories": [
      {
        "chest": {
          "Items": [
            {
              "Slot": 0,
              "count": 6,
              "id": "minecraft:beetroot_seeds"
            },
            {
              "Slot": 1,
              "count": 1,
              "components": {
                "minecraft:enchantments": {
                  "levels": {
                    "minecraft:protection": 3,
                    "ars_nouveau:mana_regen": 3
                  }
                }
              },
              "id": "minecraft:diamond_leggings"
            },
            {
              "Slot": 2,
              "count": 1,
              "components": {
                "minecraft:enchantments": {
                  "levels": {
                    "ars_nouveau:mana_regen": 3
                  }
                }
              },
              "id": "minecraft:diamond_leggings"
            },
            {
              "Slot": 3,
              "count": 17,
              "id": "minecraft:iron_ingot"
            },
            {
              "Slot": 4,
              "count": 1,
              "id": "cardiac:life_bottle"
            }
          ]
        },
        "uuid": [
          -777886662,
          -43627786,
          -2114708613,
          -1931975085
        ]
      }
    ],
    "uuid": [
      2007033184,
      245714814,
      -1667059682,
      -683526658
    ],
    "seed": 2176327028546963522,
    "name": "{\"translate\":\"container.chest\"}",
    "blockType": 0,
    "key": "lootr/7/77/77a0e560-0ea5-4f7e-9ca2-b01ed74235fe",
    "dimension": "minecraft:the_end",
    "hasBeenOpened": 1,
    "position": [
      4206,
      132,
      72
    ],
    "size": 27,
    "actualOpeners": [
      [
        -777886662,
        -43627786,
        -2114708613,
        -1931975085
      ]
    ],
    "table": "minecraft:chests/end_city_treasure"
  },
  "DataVersion": 3955,
  "brewinandchewin:data_version": 100
}