{
  "data": {
    "type": 0,
    "openers": [
      [
        -777886662,
        -43627786,
        -2114708613,
        -1931975085
      ]
    ],
    "inventories": [
      {
        "chest": {
          "Items": [
            {
              "Slot": 0,
              "count": 4,
              "id": "minecraft:bread"
            },
            {
              "Slot": 1,
              "count": 1,
              "components": {
                "minecraft:damage": 194
              },
              "id": "minecraft:iron_axe"
            },
            {
              "Slot": 2,
              "count": 1,
              "components": {
                "minecraft:damage": 207
              },
              "id": "minecraft:iron_axe"
            },
            {
              "Slot": 3,
              "count": 1,
              "components": {
                "minecraft:damage": 206
              },
              "id": "minecraft:iron_axe"
            },
            {
              "Slot": 4,
              "count": 1,
              "components": {
                "minecraft:damage": 1496
              },
              "id": "minecraft:diamond_pickaxe"
            },
            {
              "Slot": 5,
              "count": 1,
              "components": {
                "minecraft:damage": 301
              },
              "id": "minecraft:shield"
            },
            {
              "Slot": 6,
              "count": 16,
              "id": "minecraft:arrow"
            },
            {
              "Slot": 7,
              "count": 8,
              "id": "minecraft:melon_slice"
            },
            {
              "Slot": 8,
              "count": 2,
              "id": "minecraft:carrot"
            }
          ]
        },
        "uuid": [
          -777886662,
          -43627786,
          -2114708613,
          -1931975085
        ]
      }
    ],
    "uuid": [
      -83438604,
      921718202,
      -2013895250,
      27601063
    ],
    "seed": -4082564089243540026,
    "name": "{\"translate\":\"container.chest\"}",
    "blockType": 0,
    "key": "lootr/f/fb/fb06d3f4-36f0-4dba-87f6-65ae01a528a7",
    "dimension": "minecraft:overworld",
    "hasBeenOpened": 1,
    "position": [
      -2508,
      46,
      -487
    ],
    "size": 27,
    "actualOpeners": [
      [
        -777886662,
        -43627786,
        -2114708613,
        -1931975085
      ]
    ],
    "table": "stoneholm:bedroom"
  },
  "DataVersion": 3955,
  "brewinandchewin:data_version": 100
}