{
  "data": {
    "type": 0,
    "openers": [
      [
        1433557250,
        -1386395105,
        -1629274564,
        1643515946
      ]
    ],
    "inventories": [
      {
        "chest": {
          "Items": [
            {
              "Slot": 0,
              "count": 1,
              "id": "minecraft:glow_berries"
            },
            {
              "Slot": 1,
              "count": 2,
              "id": "minecraft:sculk_vein"
            },
            {
              "Slot": 2,
              "count": 2,
              "id": "minecraft:cobweb"
            },
            {
              "Slot": 3,
              "count": 2,
              "id": "minecraft:book"
            }
          ]
        },
        "uuid": [
          1433557250,
          -1386395105,
          -1629274564,
          1643515946
        ]
      }
    ],
    "uuid": [
      211549434,
      -1470872029,
      -1769365300,
      -1630300645
    ],
    "seed": 7790744337381928697,
    "name": "{\"translate\":\"container.barrel\"}",
    "blockType": 2,
    "key": "lootr/0/0c/0c9bfcfa-a854-4623-9689-a0cc9ed3961b",
    "dimension": "minecraft:overworld",
    "hasBeenOpened": 1,
    "position": [
      517,
      -40,
      164
    ],
    "size": 27,
    "actualOpeners": [
      [
        1433557250,
        -1386395105,
        -1629274564,
        1643515946
      ]
    ],
    "table": "ancient_cities:ancient_city_barrel"
  },
  "DataVersion": 3955,
  "brewinandchewin:data_version": 100
}