{
  "data": {
    "type": 0,
    "openers": [
      [
        -777886662,
        -43627786,
        -2114708613,
        -1931975085
      ]
    ],
    "inventories": [
      {
        "chest": {
          "Items": [
            {
              "Slot": 4,
              "count": 1,
              "id": "minecraft:quartz"
            },
            {
              "Slot": 9,
              "count": 1,
              "id": "minecraft:amethyst_shard"
            },
            {
              "Slot": 14,
              "count": 2,
              "id": "minecraft:quartz"
            },
            {
              "Slot": 15,
              "count": 1,
              "id": "minecraft:amethyst_shard"
            },
            {
              "Slot": 21,
              "count": 1,
              "id": "minecraft:amethyst_shard"
            },
            {
              "Slot": 24,
              "count": 1,
              "id": "minecraft:amethyst_shard"
            }
          ]
        },
        "uuid": [
          -777886662,
          -43627786,
          -2114708613,
          -1931975085
        ]
      }
    ],
    "uuid": [
      -1367666799,
      -1328920848,
      -1347689793,
      -267264217
    ],
    "seed": 6703817661105513553,
    "name": "{\"translate\":\"container.barrel\"}",
    "blockType": 2,
    "key": "lootr/a/ae/ae7b0f91-b0ca-46f0-afab-e2bff011df27",
    "dimension": "minecraft:the_nether",
    "hasBeenOpened": 1,
    "position": [
      -795,
      74,
      -1376
    ],
    "size": 27,
    "actualOpeners": [
      [
        -777886662,
        -43627786,
        -2114708613,
        -1931975085
      ]
    ],
    "table": "incendium:sanctum/junk_loot"
  },
  "DataVersion": 3955,
  "brewinandchewin:data_version": 100
}