{
  "data": {
    "type": 0,
    "openers": [
      [
        -1678841899,
        1864648116,
        -1393378093,
        -894335838
      ],
      [
        -777886662,
        -43627786,
        -2114708613,
        -1931975085
      ]
    ],
    "inventories": [
      {
        "chest": {
          "Items": []
        },
        "uuid": [
          -1678841899,
          1864648116,
          -1393378093,
          -894335838
        ]
      },
      {
        "chest": {
          "Items": [
            {
              "Slot": 3,
              "count": 1,
              "id": "minecraft:iron_ingot"
            },
            {
              "Slot": 14,
              "count": 1,
              "id": "minecraft:lapis_lazuli"
            },
            {
              "Slot": 16,
              "count": 1,
              "id": "minecraft:iron_ingot"
            },
            {
              "Slot": 23,
              "count": 2,
              "id": "minecraft:lapis_lazuli"
            }
          ]
        },
        "uuid": [
          -777886662,
          -43627786,
          -2114708613,
          -1931975085
        ]
      }
    ],
    "uuid": [
      -1107857815,
      -1699197336,
      -1799935815,
      -1306832197
    ],
    "seed": 6848661849633642105,
    "name": "{\"translate\":\"container.chest\"}",
    "blockType": 0,
    "key": "lootr/b/bd/bdf76e69-9ab8-4e68-94b7-28b9b21b52bb",
    "dimension": "minecraft:overworld",
    "hasBeenOpened": 1,
    "position": [
      -3677,
      -34,
      2728
    ],
    "size": 27,
    "actualOpeners": [
      [
        -1678841899,
        1864648116,
        -1393378093,
        -894335838
      ],
      [
        -777886662,
        -43627786,
        -2114708613,
        -1931975085
      ]
    ],
    "table": "betterstrongholds:chests/treasure"
  },
  "DataVersion": 3955,
  "brewinandchewin:data_version": 100
}