{
  "data": {
    "type": 0,
    "openers": [
      [
        -777886662,
        -43627786,
        -2114708613,
        -1931975085
      ]
    ],
    "inventories": [
      {
        "chest": {
          "Items": [
            {
              "Slot": 2,
              "count": 1,
              "id": "minecraft:map"
            },
            {
              "Slot": 6,
              "count": 1,
              "id": "minecraft:bread"
            },
            {
              "Slot": 7,
              "count": 2,
              "id": "minecraft:bread"
            },
            {
              "Slot": 9,
              "count": 1,
              "id": "minecraft:map"
            },
            {
              "Slot": 11,
              "count": 1,
              "id": "minecraft:bread"
            },
            {
              "Slot": 16,
              "count": 1,
              "id": "minecraft:map"
            },
            {
              "Slot": 18,
              "count": 1,
              "id": "minecraft:bread"
            },
            {
              "Slot": 20,
              "count": 1,
              "components": {
                "relics:data": {
                  "abilities": {
                    "abilities": {
                      "runner": {
                        "stats": {
                          "speed": {
                            "initialValue": 0.79335
                          }
                        },
                        "lock": {
                          "breaks": 5
                        },
                        "research": {
                          "links": {},
                          "researched": 0
                        },
                        "extender": {
                          "ticking": 0,
                          "cooldown": 0,
                          "cooldownCap": 0
                        },
                        "points": 0
                      }
                    }
                  },
                  "leveling": {
                    "luck": 0,
                    "experience": 0,
                    "level": 0,
                    "points": 0
                  }
                }
              },
              "id": "artifacts:running_shoes"
            },
            {
              "Slot": 26,
              "count": 1,
              "id": "minecraft:bread"
            }
          ]
        },
        "uuid": [
          -777886662,
          -43627786,
          -2114708613,
          -1931975085
        ]
      }
    ],
    "uuid": [
      744667662,
      1730104415,
      -1081504543,
      1235360544
    ],
    "seed": -2965380876539700478,
    "name": "{\"translate\":\"container.chest\"}",
    "blockType": 0,
    "key": "lootr/2/2c/2c62ba0e-671f-4c5f-bf89-8ce149a21b20",
    "dimension": "minecraft:overworld",
    "hasBeenOpened": 1,
    "position": [
      -4788,
      69,
      1877
    ],
    "size": 27,
    "actualOpeners": [
      [
        -777886662,
        -43627786,
        -2114708613,
        -1931975085
      ]
    ],
    "table": "minecraft:chests/village/village_cartographer"
  },
  "DataVersion": 3955,
  "brewinandchewin:data_version": 100
}