{
  "data": {
    "type": 0,
    "openers": [
      [
        -777886662,
        -43627786,
        -2114708613,
        -1931975085
      ]
    ],
    "inventories": [
      {
        "chest": {
          "Items": [
            {
              "Slot": 2,
              "count": 4,
              "id": "minecraft:crying_obsidian"
            },
            {
              "Slot": 3,
              "count": 1,
              "id": "minecraft:diamond_sword"
            },
            {
              "Slot": 4,
              "count": 1,
              "id": "minecraft:diamond_leggings"
            },
            {
              "Slot": 5,
              "count": 21,
              "id": "minecraft:spectral_arrow"
            },
            {
              "Slot": 6,
              "count": 4,
              "id": "minecraft:diamond"
            },
            {
              "Slot": 7,
              "count": 1,
              "id": "minecraft:netherite_upgrade_smithing_template"
            },
            {
              "Slot": 8,
              "count": 1,
              "id": "create_dragons_plus:blaze_upgrade_smithing_template"
            },
            {
              "Slot": 9,
              "count": 3,
              "id": "silentgear:crimson_iron_ingot"
            },
            {
              "Slot": 10,
              "count": 4,
              "id": "silentgear:blaze_gold_ingot"
            },
            {
              "Slot": 11,
              "count": 6,
              "id": "silentgear:blaze_gold_nugget"
            },
            {
              "Slot": 12,
              "count": 21,
              "id": "ars_nouveau:split_arrow"
            },
            {
              "Slot": 13,
              "count": 1,
              "id": "farmersdelight:diamond_knife"
            }
          ]
        },
        "uuid": [
          -777886662,
          -43627786,
          -2114708613,
          -1931975085
        ]
      }
    ],
    "uuid": [
      52106733,
      2058964013,
      -1622528720,
      476211509
    ],
    "seed": -6007921310026315226,
    "name": "{\"translate\":\"container.chest\"}",
    "blockType": 0,
    "key": "lootr/0/03/031b15ed-7ab9-4c2d-9f4a-2d301c626935",
    "dimension": "minecraft:the_nether",
    "hasBeenOpened": 1,
    "position": [
      2953,
      66,
      4131
    ],
    "size": 27,
    "actualOpeners": [
      [
        -777886662,
        -43627786,
        -2114708613,
        -1931975085
      ]
    ],
    "table": "minecraft:chests/bastion_treasure"
  },
  "DataVersion": 3955,
  "brewinandchewin:data_version": 100
}