{
  "data": {
    "type": 0,
    "openers": [
      [
        -777886662,
        -43627786,
        -2114708613,
        -1931975085
      ]
    ],
    "inventories": [
      {
        "chest": {
          "Items": [
            {
              "Slot": 0,
              "count": 1,
              "id": "minecraft:iron_leggings"
            },
            {
              "Slot": 1,
              "count": 8,
              "id": "minecraft:raw_copper"
            },
            {
              "Slot": 2,
              "count": 2,
              "id": "minecraft:raw_gold"
            },
            {
              "Slot": 3,
              "count": 6,
              "id": "minecraft:gunpowder"
            }
          ]
        },
        "uuid": [
          -777886662,
          -43627786,
          -2114708613,
          -1931975085
        ]
      }
    ],
    "uuid": [
      -1337988591,
      1603029544,
      -2106074593,
      1222841096
    ],
    "seed": 4331298893008793197,
    "name": "{\"translate\":\"container.chest\"}",
    "blockType": 0,
    "key": "lootr/b/b0/b03fea11-5f8c-4a28-8277-da1f48e31308",
    "dimension": "minecraft:overworld",
    "hasBeenOpened": 1,
    "position": [
      -1183,
      -28,
      -3838
    ],
    "size": 27,
    "actualOpeners": [
      [
        -777886662,
        -43627786,
        -2114708613,
        -1931975085
      ]
    ],
    "table": "artifacts:chests/campsite_chest"
  },
  "DataVersion": 3955,
  "brewinandchewin:data_version": 100
}