{
  "data": {
    "type": 0,
    "openers": [
      [
        -777886662,
        -43627786,
        -2114708613,
        -1931975085
      ]
    ],
    "inventories": [
      {
        "chest": {
          "Items": []
        },
        "uuid": [
          -777886662,
          -43627786,
          -2114708613,
          -1931975085
        ]
      }
    ],
    "uuid": [
      -2127510326,
      1730627344,
      -1710258102,
      -126229622
    ],
    "seed": 7545220950180179509,
    "name": "{\"translate\":\"container.chest\"}",
    "blockType": 0,
    "key": "lootr/8/81/8130c4ca-6727-4710-9a0f-884af879e38a",
    "dimension": "minecraft:overworld",
    "hasBeenOpened": 1,
    "position": [
      1179,
      64,
      -311
    ],
    "size": 27,
    "actualOpeners": [
      [
        -777886662,
        -43627786,
        -2114708613,
        -1931975085
      ]
    ],
    "table": "minecraft:chests/village/village_temple"
  },
  "DataVersion": 3955,
  "brewinandchewin:data_version": 100
}