{
  "data": {
    "type": 0,
    "openers": [
      [
        1433557250,
        -1386395105,
        -1629274564,
        1643515946
      ]
    ],
    "inventories": [
      {
        "chest": {
          "Items": [
            {
              "Slot": 4,
              "count": 1,
              "id": "minecraft:carrot"
            },
            {
              "Slot": 5,
              "count": 1,
              "id": "minecraft:wheat"
            },
            {
              "Slot": 6,
              "count": 1,
              "id": "minecraft:potato"
            },
            {
              "Slot": 8,
              "count": 1,
              "id": "minecraft:apple"
            },
            {
              "Slot": 13,
              "count": 2,
              "id": "minecraft:potato"
            },
            {
              "Slot": 14,
              "count": 1,
              "id": "minecraft:wheat"
            },
            {
              "Slot": 16,
              "count": 4,
              "id": "minecraft:carrot"
            },
            {
              "Slot": 17,
              "count": 1,
              "id": "minecraft:apple"
            },
            {
              "Slot": 20,
              "count": 1,
              "id": "minecraft:carrot"
            },
            {
              "Slot": 26,
              "count": 1,
              "id": "minecraft:carrot"
            }
          ]
        },
        "uuid": [
          1433557250,
          -1386395105,
          -1629274564,
          1643515946
        ]
      }
    ],
    "uuid": [
      125054075,
      1672628357,
      -1131403623,
      -890812271
    ],
    "seed": 4632787143969742924,
    "name": "{\"translate\":\"container.chest\"}",
    "blockType": 0,
    "key": "lootr/0/07/07742c7b-63b2-4885-bc90-2699cae74891",
    "dimension": "amplidim:overworld",
    "hasBeenOpened": 1,
    "position": [
      873,
      203,
      366
    ],
    "size": 27,
    "actualOpeners": [
      [
        1433557250,
        -1386395105,
        -1629274564,
        1643515946
      ]
    ],
    "table": "terralith:village/fortified/tavern_upstairs"
  },
  "DataVersion": 3955,
  "brewinandchewin:data_version": 100
}